xrandpwm/__init__.py
xrandpwm/command.py
xrandpwm/monitorbundle.py
xrandpwm/monitorstate.py
xrandpwm/screenstate.py
xrandpwm/utils.py
xrandpwm-0.0.8.dist-info/LICENSE
xrandpwm-0.0.8.dist-info/METADATA
xrandpwm-0.0.8.dist-info/WHEEL
xrandpwm-0.0.8.dist-info/top_level.txt
xrandpwm-0.0.8.dist-info/RECORD
